{
  "main": {
    "id": "f79ee63a1fdceebb",
    "type": "split",
    "children": [
      {
        "id": "108ff670bcc92a0f",
        "type": "tabs",
        "children": [
          {
            "id": "ff6a10a0cbdf5eed",
            "type": "leaf",
            "state": {
              "type": "graph",
              "state": {}
            }
          }
        ]
      }
    ],
    "direction": "vertical"
  },
  "left": {
    "id": "296db39ec59d7c76",
    "type": "split",
    "children": [
      {
        "id": "442e9100e656e7cf",
        "type": "tabs",
        "children": [
          {
            "id": "6816e75aee07d7f4",
            "type": "leaf",
            "state": {
              "type": "file-explorer",
              "state": {
                "sortOrder": "alphabetical"
              }
            }
          },
          {
            "id": "1f734eefa4a45759",
            "type": "leaf",
            "state": {
              "type": "search",
              "state": {
                "query": "call",
                "matchingCase": false,
                "explainSearch": false,
                "collapseAll": false,
                "extraContext": false,
                "sortOrder": "alphabetical"
              }
            }
          },
          {
            "id": "5701823eedd0d619",
            "type": "leaf",
            "state": {
              "type": "bookmarks",
              "state": {}
            }
          }
        ]
      }
    ],
    "direction": "horizontal",
    "width": 258.5
  },
  "right": {
    "id": "fcc33a9b8a257313",
    "type": "split",
    "children": [
      {
        "id": "e394e23e5f797b7b",
        "type": "tabs",
        "children": [
          {
            "id": "e1e94e4afb05c965",
            "type": "leaf",
            "state": {
              "type": "backlink",
              "state": {
                "collapseAll": false,
                "extraContext": false,
                "sortOrder": "alphabetical",
                "showSearch": false,
                "searchQuery": "",
                "backlinkCollapsed": false,
                "unlinkedCollapsed": true
              }
            }
          },
          {
            "id": "404e9c3fd2b657c3",
            "type": "leaf",
            "state": {
              "type": "outgoing-link",
              "state": {
                "linksCollapsed": false,
                "unlinkedCollapsed": true
              }
            }
          },
          {
            "id": "6bf7ef100d51a56d",
            "type": "leaf",
            "state": {
              "type": "tag",
              "state": {
                "sortOrder": "frequency",
                "useHierarchy": true
              }
            }
          },
          {
            "id": "4ac787a3a17d3a94",
            "type": "leaf",
            "state": {
              "type": "outline",
              "state": {}
            }
          },
          {
            "id": "45f16e2740ad8887",
            "type": "leaf",
            "state": {
              "type": "initiative-tracker-view",
              "state": {}
            }
          },
          {
            "id": "e13914ecd64429c8",
            "type": "leaf",
            "state": {
              "type": "advanced-tables-toolbar",
              "state": {}
            }
          }
        ]
      }
    ],
    "direction": "horizontal",
    "width": 200,
    "collapsed": true
  },
  "left-ribbon": {
    "hiddenItems": {
      "fantasy-content-generator:Fantasy Generators": false,
      "obsidian-extract-pdf-highlights:PDF Highlights": false,
      "switcher:Open quick switcher": false,
      "graph:Open graph view": false,
      "canvas:Create new canvas": false,
      "daily-notes:Open today's daily note": false,
      "command-palette:Open command palette": false,
      "markdown-importer:Open format converter": false,
      "random-note:Open random note": false,
      "templates:Insert template": false,
      "initiative-tracker:Intiative Tracker Encounter Builder": false,
      "templater-obsidian:Templater": false,
      "table-editor-obsidian:Advanced Tables Toolbar": false,
      "obsidian-excalidraw-plugin:Create new drawing": false
    }
  },
  "active": "ff6a10a0cbdf5eed",
  "lastOpenFiles": [
    "Diario/2023/08-August/2023-08-09-Wednesday.md",
    "Ficción/D&D/Waterdeep Dragon Heist/1- Entidades/Lander Severian.md",
    "Ficción/D&D/Waterdeep Dragon Heist/1- Entidades/Nemeia.md",
    "Ficción/D&D/Waterdeep Dragon Heist/1- Entidades/Renaer Neverember.md",
    "Ficción/D&D/Waterdeep Dragon Heist/1- Entidades/Talisolvanar ”Tally” Fellbranch.md",
    "Ficción/D&D/Waterdeep Dragon Heist/2- Lugares/El Portal Bostezante.md",
    "z_attachments/Nemeia.png",
    "z_attachments/D&D/Nemeia.png",
    "Diario/2023/08-August/2023-08-06-Sunday.md",
    "Ficción/D&D/Waterdeep Dragon Heist/1- Entidades/Deidades/Ruthya.md",
    "Ficción/D&D/Waterdeep Dragon Heist/1- Entidades/Deidades",
    "Diario/2023/08-August/2023-08-07-Monday.md",
    "Diario/2023/08-August/2023-08-04-Friday.md",
    "Diario/2023/08-August/2023-08-03-Thursday.md",
    "Ficción/D&D/Waterdeep Dragon Heist/5- Ideas/Avril - Zarrai en el balcon Ashrunner.md",
    "Ficción/D&D/Waterdeep Dragon Heist/7- Narrativa/2 - Bailes y Vitrales.md",
    "Ficción/D&D/Waterdeep Dragon Heist/7- Narrativa/1B - Arte.md",
    "Ficción/D&D/Waterdeep Dragon Heist/7- Narrativa/1 - Un Amigo en Apuros.md",
    "Ficción/D&D/Waterdeep Dragon Heist/7- Narrativa/0 - La Bóveda - Preludio.md",
    "Ficción/CloudCore/6 - Fauna y Flora/Val'Bathun.md",
    "Ficción/CloudCore/7 - Líneas de tiempo/Historia Completa.md",
    "Ficción/CloudCore/8 - Organizaciones/Protectores Espejismo.md",
    "Ficción/CloudCore/5 - Civilizaciones/La ciudad de Azula.md",
    "Ficción/CloudCore/2 - Mapas/Mapa.md",
    "Ficción/CloudCore/1 - Personajes/Personaje de Prueba.md",
    "Ficción/CloudCore/4 - Metafísica/Conceptos de Cloudcore/Nimbus.md",
    "Ficción/CloudCore/5 - Metafísica/Cloudcore/Untitled",
    "Ficción/CloudCore/4 - Metafísica/Conceptos de Cloudcore",
    "Ficción/CloudCore/5 - Civilizaciones",
    "Ficción/CloudCore/9 - Cultura",
    "Ficción/CloudCore/8 - Organizaciones",
    "Ficción/CloudCore/7 - Líneas de tiempo",
    "Ficción/CloudCore/6 - Fauna y Flora",
    "Ficción/CloudCore/4 - Metafísica",
    "Ficción/CloudCore/5 - Regiones",
    "Ficción/D&D/Waterdeep Dragon Heist/1- Entidades/Squiddly.md",
    "z_attachments/D&D/squiddly.png",
    "z_attachments/D&D/some mf tiefling.png",
    "Programación/Laburo/Twillio/Lambda.md",
    "Programación/Laburo/Twillio/Conexión inicial.md",
    "z_attachments/D&D/Shock2.jpg",
    "z_attachments/Daily Note Images/Dwaing.png",
    "z_attachments/D&D/MansiónTrollskullAfuera.png",
    "z_attachments/D&D/ConstanzaAshrunner.jpg",
    "z_attachments/D&D/Durnan.png",
    "z_attachments/D&D/TrollskullAlley.png"
  ]
}